inquest/__init__.py
inquest/comms/client_consumer.py
inquest/comms/client_provider.py
inquest/comms/exception_sender.py
inquest/comms/heartbeat.py
inquest/comms/log_sender.py
inquest/comms/module_sender.py
inquest/comms/trace_set_subscriber.py
inquest/comms/utils.py
inquest/comms/version_checker.py
inquest/file_module_resolver.py
inquest/file_sender.py
inquest/hotpatch.py
inquest/injection/ast_injector.py
inquest/injection/code_reassigner.py
inquest/injection/codegen.py
inquest/logging.py
inquest/module_tree.py
inquest/probe.py
inquest/resources/.gitkeep
inquest/runner.py
inquest/test/__init__.py
inquest/test/absolutize_test.py
inquest/test/ast_injector_test.py
inquest/test/ast_test.py
inquest/test/diff_test.py
inquest/test/embed_test_module/__init__.py
inquest/test/embed_test_module/test_imported_module.py
inquest/test/embed_test_module/test_unimported_module.py
inquest/test/module_tree_test.py
inquest/test/probe_test.py
inquest/test/probe_test_module/__init__.py
inquest/test/probe_test_module/test_imported_module.py
inquest/test/sample.py
inquest/test/test_codegen.py
inquest/utils/chunk.py
inquest/utils/exceptions.py
inquest/utils/has_stack.py
inquest/utils/logging.py
inquest/utils/version.py
inquest-0.4.4.dist-info/WHEEL
inquest-0.4.4.dist-info/METADATA
inquest-0.4.4.dist-info/RECORD
