Metadata-Version: 2.1
Name: inquest
Version: 0.4.4
Summary: 
License: LGPL-3.0+
Author: Shalom Yiblet
Author-email: shalom.yiblet@gmail.com
Requires-Python: >=3.7,<4.0
Classifier: License :: OSI Approved :: GNU Lesser General Public License v3 or later (LGPLv3+)
Classifier: Programming Language :: Python :: 3
Classifier: Programming Language :: Python :: 3.7
Classifier: Programming Language :: Python :: 3.8
Requires-Dist: aiohttp (>=3.6.2,<4.0.0)
Requires-Dist: gql (==3.0.0a0)
Requires-Dist: janus (>=0.5.0,<0.6.0)
Requires-Dist: pandas (>=1.0.3,<2.0.0)
